yzrpc/__init__.py
yzrpc/__main__.py
yzrpc/_local.py
yzrpc/_types.py
yzrpc/client.py
yzrpc/exceptions.py
yzrpc/proto.py
yzrpc/schema.py
yzrpc/server.py
yzrpc/servicer.py
yzrpc/__pycache__/__init__.cpython-37.pyc
yzrpc/__pycache__/__main__.cpython-37.pyc
yzrpc/__pycache__/_types.cpython-37.pyc
yzrpc/__pycache__/client.cpython-37.pyc
yzrpc/__pycache__/exceptions.cpython-37.pyc
yzrpc/__pycache__/local.cpython-37.pyc
yzrpc/__pycache__/proto.cpython-37.pyc
yzrpc/__pycache__/schema.cpython-37.pyc
yzrpc/__pycache__/server.cpython-37.pyc
yzrpc/__pycache__/servicer.cpython-37.pyc
yzrpc/commands/__init__.py
yzrpc/commands/createapp.py
yzrpc/commands/createproject.py
yzrpc/commands/generatemodule.py
yzrpc/commands/generateproto.py
yzrpc/commands/runconsole.py
yzrpc/commands/runserver.py
yzrpc/commands/runtest.py
yzrpc/commands/__pycache__/__init__.cpython-37.pyc
yzrpc/commands/__pycache__/createapp.cpython-37.pyc
yzrpc/commands/__pycache__/createproject.cpython-37.pyc
yzrpc/commands/__pycache__/generate.cpython-37.pyc
yzrpc/commands/__pycache__/runserver.cpython-37.pyc
yzrpc/config/__init__.py
yzrpc/config/default_settings.py
yzrpc/config/__pycache__/__init__.cpython-37.pyc
yzrpc/config/__pycache__/default_settings.cpython-37.pyc
yzrpc/extensions/__init__.py
yzrpc/middlewares/__init__.py
yzrpc/templates/app_template/apps/app_name/__init__.py
yzrpc/templates/app_template/apps/app_name/controllers.py
yzrpc/templates/app_template/apps/app_name/models.py
yzrpc/templates/app_template/apps/app_name/schemas.py
yzrpc/templates/app_template/apps/app_name/tests.py.tmpl
yzrpc/templates/app_template/apps/app_name/views.py.tmpl
yzrpc/templates/project_template/.gitignore
yzrpc/templates/project_template/README.md.tmpl
yzrpc/templates/project_template/requirements.txt
yzrpc/templates/project_template/docs/install_explain.md
yzrpc/templates/project_template/docs/supervisor.ini.tmpl
yzrpc/templates/project_template/migrations/README.md
yzrpc/templates/project_template/src/__init__.py
yzrpc-0.1.dist-info/LICENSE
yzrpc-0.1.dist-info/METADATA
yzrpc-0.1.dist-info/WHEEL
yzrpc-0.1.dist-info/entry_points.txt
yzrpc-0.1.dist-info/top_level.txt
yzrpc-0.1.dist-info/zip-safe
yzrpc-0.1.dist-info/RECORD
