Metadata-Version: 2.1
Name: yzrpc
Version: 0.1
Summary: A gRPC framework for automatically generating protobuf files.
Home-page: https://github.com/ml444/yz-rpc
Author: cml
Author-email: caimengli0660@gmail.com
License: Apache License Version 2.0
Keywords: rpc,grpc,async,yzrpc
Platform: UNKNOWN
Classifier: Development Status :: 4 - Beta
Classifier: Environment :: Web Environment
Classifier: Intended Audience :: Developers
Classifier: Operating System :: MacOS
Classifier: Operating System :: MacOS :: MacOS X
Classifier: Operating System :: POSIX :: BSD
Classifier: Operating System :: POSIX :: Linux
Classifier: License :: OSI Approved :: Apache Software License
Classifier: Programming Language :: Python
Classifier: Programming Language :: Python :: 3
Classifier: Programming Language :: Python :: 3.6
Classifier: Programming Language :: Python :: 3.7
Classifier: Programming Language :: Python :: 3.8
Classifier: Topic :: Internet
Classifier: Topic :: Software Development :: Build Tools
Classifier: Topic :: Software Development :: Libraries :: Python Modules
Requires-Python: >=3.6
Requires-Dist: grpcio (>=1.35.0)
Requires-Dist: grpcio-tools (>=1.35.0)
Requires-Dist: Jinja2 (<3,>=2.11.3)
Requires-Dist: pydantic (<2,>=1.8)
